pyramid_resource.py
pyramid_resource-0.5.1.dist-info/LICENSE
pyramid_resource-0.5.1.dist-info/METADATA
pyramid_resource-0.5.1.dist-info/WHEEL
pyramid_resource-0.5.1.dist-info/top_level.txt
pyramid_resource-0.5.1.dist-info/RECORD
