Metadata-Version: 2.1
Name: pyramid-resource
Version: 0.5.1
Summary: A simple base resource class for Pyramid traversal.
Home-page: https://github.com/luhn/pyramid-resource
Author: Theron Luhn
Author-email: theron@luhn.com
Classifier: Development Status :: 4 - Beta
Classifier: Framework :: Pyramid
Classifier: Intended Audience :: Developers
Classifier: License :: OSI Approved :: MIT License
Classifier: Operating System :: OS Independent
Classifier: Programming Language :: Python :: 3 :: Only
Classifier: Programming Language :: Python :: 3
Classifier: Programming Language :: Python :: 3.8
Classifier: Programming Language :: Python :: 3.9
Classifier: Programming Language :: Python :: 3.10
Classifier: Programming Language :: Python :: 3.11
Classifier: Programming Language :: Python :: 3.12
Classifier: Programming Language :: Python :: Implementation :: CPython
Classifier: Programming Language :: Python :: Implementation :: PyPy
Classifier: Programming Language :: Python
Requires-Python: >=3.8
License-File: LICENSE
Requires-Dist: pyramid >=1.7
Provides-Extra: linting
Requires-Dist: ruff ~=0.7.0 ; extra == 'linting'
Provides-Extra: testing
Requires-Dist: pytest ~=8.3 ; extra == 'testing'
Requires-Dist: webtest ~=3.0 ; extra == 'testing'
